setup.py
gradlepy/__init__.py
gradlepy/run.py
gradlepy.egg-info/PKG-INFO
gradlepy.egg-info/SOURCES.txt
gradlepy.egg-info/dependency_links.txt
gradlepy.egg-info/top_level.txt