Metadata-Version: 1.0
Name: gradlepy
Version: 0.1.2
Summary: Wrapper for calling Gradle from Python
Home-page: http://github.com/Gohla/gradlepy
Author: Gabriel Konat
Author-email: gabrielkonat@gmail.com
License: Apache 2.0
Platform: UNKNOWN
